book_review_scraper/__init__.py
book_review_scraper/bookstores.py
book_review_scraper/cache.py
book_review_scraper/config.py
book_review_scraper/exceptions.py
book_review_scraper/helper.py
book_review_scraper/parsing.py
book_review_scraper/review.py
book_review_scraper/scraper.py
book_review_scraper-1.0.4.dist-info/LICENSE.txt
book_review_scraper-1.0.4.dist-info/METADATA
book_review_scraper-1.0.4.dist-info/RECORD
book_review_scraper-1.0.4.dist-info/WHEEL
book_review_scraper-1.0.4.dist-info/top_level.txt
