Metadata-Version: 2.1
Name: book-review-scraper
Version: 1.0.4
Summary: simple book review scraper
Home-page: https://github.com/bookbookscsc/scraper
Author: minomi
Author-email: 5minhominho@gmail.com
License: MIT
Keywords: book,review
Platform: UNKNOWN
Classifier: Development Status :: 4 - Beta
Classifier: Intended Audience :: Developers
Classifier: Topic :: Software Development :: Build Tools
Classifier: License :: OSI Approved :: MIT License
Classifier: Programming Language :: Python
Classifier: Programming Language :: Python :: 3.6
Classifier: Programming Language :: Python :: Implementation :: CPython
Requires-Python: >=3.6.0
Requires-Dist: requests-html (==0.9.0)
